non_blocking_pipe/__init__.py
non_blocking_pipe/pipe.py
non_blocking_pipe-0.3.dist-info/METADATA
non_blocking_pipe-0.3.dist-info/WHEEL
non_blocking_pipe-0.3.dist-info/top_level.txt
non_blocking_pipe-0.3.dist-info/RECORD
