Metadata-Version: 2.1
Name: non-blocking-pipe
Version: 0.3
Summary: non-blocking pipe
Home-page: https://github.com/maxtwen/Non-Blocking-Pipe
Author: Maksim Afanasevsky
Author-email: maxtwen1@gmail.com
License: UNKNOWN
Download-URL: https://github.com/maxtwen/Non-Blocking-Pipe
Platform: UNKNOWN
